Metadata-Version: 2.1
Name: query-factory
Version: 0.1.0
Summary: Tool to organize query through factories.
Home-page: https://gitlab.com/dithyrambe/query-factory
License: MIT
Platform: UNKNOWN
Classifier: Programming Language :: Python :: 3.7
